causalbootstrapping/__init__.py
causalbootstrapping/backend.py
causalbootstrapping/cb_type_defs.py
causalbootstrapping/distEst_lib.py
causalbootstrapping/expr_extend.py
causalbootstrapping/utils.py
causalbootstrapping/workflows.py
causalbootstrapping-0.2.5.dist-info/licenses/LICENSE
causalbootstrapping-0.2.5.dist-info/METADATA
causalbootstrapping-0.2.5.dist-info/WHEEL
causalbootstrapping-0.2.5.dist-info/top_level.txt
causalbootstrapping-0.2.5.dist-info/RECORD
