Metadata-Version: 2.4
Name: causalbootstrapping
Version: 0.2.5
Summary: CausalBootstrapping is an easy-access implementation and extention of causal bootstrapping (CB) technique for causal analysis. With certain input of observational data, causal graph and variable distributions, CB resamples the data by adjusting the variable distributions which follow intended causal effects.
Home-page: https://github.com/JianqiaoMao/CausalBootstrapping
Author: Jianqiao Mao
Author-email: Jianqiao Mao <jxm1417@student.bham.ac.uk>
License:                     GNU GENERAL PUBLIC LICENSE
Project-URL: Homepage, https://github.com/JianqiaoMao/CausalBootstrapping
Requires-Python: >=3.9,<3.11
License-File: LICENSE
Requires-Dist: numpy~=1.25.0
Requires-Dist: grapl-causal==1.6.1
Requires-Dist: scipy~=1.13.1
Requires-Dist: graphviz==0.20.3
Requires-Dist: sympy~=1.13.1
Dynamic: author
Dynamic: home-page
Dynamic: license-file
Dynamic: requires-python
